{"res": {"gjskill306": {"y": 1, "x": 882, "w": 122, "h": 210}, "gjskill305": {"y": 1, "x": 644, "w": 118, "h": 212}, "gjskill304": {"y": 1, "x": 763, "w": 118, "h": 212}, "gjskill303": {"y": 1, "x": 1, "w": 220, "h": 230}, "gjskill302": {"y": 1, "x": 222, "w": 200, "h": 230}, "gjskill301": {"y": 1, "x": 423, "w": 220, "h": 218}}, "mc": {"gjskill3": {"frames": [{"y": -98, "res": "gjskill301", "x": -110}, {"y": -110, "res": "gjskill302", "x": -103}, {"y": -110, "res": "gjskill303", "x": -110}, {"y": -111, "res": "gjskill304", "x": -61}, {"y": -111, "res": "gjskill305", "x": -59}, {"y": -111, "res": "gjskill306", "x": -60}], "labels": [{"frame": 1, "end": 6, "name": "gjskill3"}], "frameRate": "8", "events": []}}}