{"res": {"jialan_002": {"y": 1, "x": 173, "w": 80, "h": 150}, "jialan_003": {"y": 1, "x": 88, "w": 84, "h": 148}, "jialan_001": {"y": 124, "x": 1, "w": 78, "h": 138}, "jialan_004": {"y": 1, "x": 1, "w": 86, "h": 122}}, "mc": {"jialan": {"frames": [{"y": -58, "res": "jialan_001", "x": -48}, {"y": -73, "res": "jialan_002", "x": -48}, {"y": -75, "res": "jialan_003", "x": -48}, {"y": -57, "res": "jialan_004", "x": -42}], "labels": [{"frame": 1, "end": 4, "name": "jialan"}], "frameRate": "8", "events": []}}}